kinjax/__init__.py
kinjax/kinjax.py
kinjax-0.0.5.dist-info/METADATA
kinjax-0.0.5.dist-info/WHEEL
kinjax-0.0.5.dist-info/top_level.txt
kinjax-0.0.5.dist-info/RECORD
