Metadata-Version: 2.1
Name: kinjax
Version: 0.0.5
Summary: This module calculates FK and Jacobian, accelerated by Jax to utilize JIT and GPU parallelization
Author: Kanghyun Kim
Author-email: kh11kim@kaist.ac.kr
Requires-Dist: jax
Requires-Dist: sympy
Requires-Dist: scipy
